hack4u_niggi/__init__.py
hack4u_niggi/courses.py
hack4u_niggi/utils.py
hack4u_niggi-7.1.0.dist-info/METADATA
hack4u_niggi-7.1.0.dist-info/WHEEL
hack4u_niggi-7.1.0.dist-info/top_level.txt
hack4u_niggi-7.1.0.dist-info/RECORD
